easybot/__init__.py
easybot/easybot.py
easybot-0.0.3.dist-info/LICENSE
easybot-0.0.3.dist-info/METADATA
easybot-0.0.3.dist-info/WHEEL
easybot-0.0.3.dist-info/top_level.txt
easybot-0.0.3.dist-info/RECORD
